{
  "main": {
    "id": "079edc56e4e7ab17",
    "type": "split",
    "children": [
      {
        "id": "560f806afacb1b7a",
        "type": "tabs",
        "children": [
          {
            "id": "5004cc564f72d480",
            "type": "leaf",
            "state": {
              "type": "markdown",
              "state": {
                "file": "_posts/2023-02-01-Coloumb.md",
                "mode": "source",
                "source": false
              }
            }
          },
          {
            "id": "f56063d21c255229",
            "type": "leaf",
            "state": {
              "type": "markdown",
              "state": {
                "file": "_posts/diary/2023-06-10-19.md",
                "mode": "source",
                "source": false
              }
            }
          },
          {
            "id": "817ff6bcfe91d9e6",
            "type": "leaf",
            "state": {
              "type": "markdown",
              "state": {
                "file": "_posts/talks/2021-11-23-electromagnetism.md",
                "mode": "source",
                "source": false
              }
            }
          },
          {
            "id": "71a82fb1fac9d135",
            "type": "leaf",
            "state": {
              "type": "markdown",
              "state": {
                "file": "_posts/diary/2023-07-08-21.md",
                "mode": "source",
                "source": false
              }
            }
          },
          {
            "id": "5aaa8a97a864cc55",
            "type": "leaf",
            "state": {
              "type": "markdown",
              "state": {
                "file": "visualization.md",
                "mode": "source",
                "source": false
              }
            }
          }
        ],
        "currentTab": 2
      }
    ],
    "direction": "vertical"
  },
  "left": {
    "id": "8577c7fee727ce18",
    "type": "split",
    "children": [
      {
        "id": "784639f3b57c835f",
        "type": "tabs",
        "children": [
          {
            "id": "c69b7ad25463c2e6",
            "type": "leaf",
            "state": {
              "type": "file-explorer",
              "state": {
                "sortOrder": "alphabetical"
              }
            }
          },
          {
            "id": "43d9983079684e3e",
            "type": "leaf",
            "state": {
              "type": "search",
              "state": {
                "query": "",
                "matchingCase": false,
                "explainSearch": false,
                "collapseAll": false,
                "extraContext": false,
                "sortOrder": "alphabetical"
              }
            }
          },
          {
            "id": "7c8c324f5d71137e",
            "type": "leaf",
            "state": {
              "type": "starred",
              "state": {}
            }
          },
          {
            "id": "6f1757a390ffea9f",
            "type": "leaf",
            "state": {
              "type": "bookmarks",
              "state": {}
            }
          }
        ]
      }
    ],
    "direction": "horizontal",
    "width": 300
  },
  "right": {
    "id": "6ef206bcfa0f9c8a",
    "type": "split",
    "children": [
      {
        "id": "1f42d707b1c2f981",
        "type": "tabs",
        "children": [
          {
            "id": "d90cd9034f1ad525",
            "type": "leaf",
            "state": {
              "type": "backlink",
              "state": {
                "file": "_posts/talks/2021-11-23-electromagnetism.md",
                "collapseAll": true,
                "extraContext": true,
                "sortOrder": "alphabetical",
                "showSearch": false,
                "searchQuery": "",
                "backlinkCollapsed": true,
                "unlinkedCollapsed": true
              }
            }
          },
          {
            "id": "323f675859ca783f",
            "type": "leaf",
            "state": {
              "type": "outgoing-link",
              "state": {
                "file": "_posts/talks/2021-11-23-electromagnetism.md",
                "linksCollapsed": false,
                "unlinkedCollapsed": true
              }
            }
          },
          {
            "id": "8ffbf7509c1ad02c",
            "type": "leaf",
            "state": {
              "type": "tag",
              "state": {
                "sortOrder": "frequency",
                "useHierarchy": true
              }
            }
          },
          {
            "id": "6fcca5507c2de9bd",
            "type": "leaf",
            "state": {
              "type": "outline",
              "state": {
                "file": "_posts/talks/2021-11-23-electromagnetism.md"
              }
            }
          }
        ],
        "currentTab": 3
      }
    ],
    "direction": "horizontal",
    "width": 300
  },
  "left-ribbon": {
    "hiddenItems": {
      "switcher:Open quick switcher": false,
      "graph:Open graph view": false,
      "canvas:Create new canvas": false,
      "daily-notes:Open today's daily note": false,
      "templates:Insert template": false,
      "command-palette:Open command palette": false
    }
  },
  "active": "817ff6bcfe91d9e6",
  "lastOpenFiles": [
    "_site/craft/index.html",
    "_posts/crafts/2024-01-08-.md",
    "_site/craft/soap-bubbles-copy.html",
    "_posts/crafts/2024-01-07-soap bubbles copy.md",
    "_site/craft/soap-bubbles.html",
    "_posts/crafts/2024-01-07-soap bubbles.md",
    "_site/craft/hyperbolic-origami-copy.html",
    "_posts/crafts/2024-01-06-hyperbolic-origami copy.md",
    "_site/craft/hyperbolic-origami.html",
    "_posts/crafts/2024-01-06-hyperbolic-origami.md",
    "_site/craft/curved-origami-copy.html",
    "_posts/crafts/2024-01-05-curved-origami copy.md",
    "_site/craft/curved-origami.html",
    "_posts/crafts/2024-01-05-curved-origami.md",
    "_site/craft/st.html",
    "_posts/crafts/2024-01-05-st.md",
    "_posts/crafts/2024-01-05-string-art copy.md",
    "_site/craft/string-art-copy.html",
    "_posts/crafts/2024-01-04-string-art copy.md",
    "_posts/crafts/2024-01-04-string-art.md",
    "_site/craft/string-art.html",
    "_posts/crafts/2024-01-04-string art.md",
    "_posts/crafts/2024-01-04-.md",
    "_posts/crafts/2024-01-0.md",
    "_posts/crafts/2024-01-03-hyperbolic-cardboard copy.md",
    "_posts/crafts/2024-01-03-hyperbolic-cardboard.md",
    "_posts/crafts/2024-01-02-weaving copy.md",
    "_site/assets/crafts/weaving/everyone.jpeg",
    "assets/crafts/weaving/everyone.jpeg",
    "_site/assets/crafts/weaving/everyone 2.jpeg",
    "assets/crafts/weaving/everyone 2.jpeg",
    "_posts/crafts/2024-01-01-polyhera copy.md",
    "_posts/crafts/2024-01-02-weaving.md",
    "_posts/talks/2023-01-23-polygons.md",
    "_posts/talks/2023-09-08-G-spaces.md",
    "_posts/talks/2023-05-11-cortex.md",
    "_posts/crafts/2024-01-01-polyhera.md",
    "_site/assets/crafts/polyhedra/dodecahedron.jpg",
    "assets/crafts/polyhedra/dodecahedron.jpg",
    "_posts/code/2022-06-05-toric.md",
    "_posts/talks/2021-11-23-electromagnetism.md",
    "_site/Pasted image 20231228123947.png",
    "Pasted image 20231228123947.png",
    "_site/Pasted image 20231228123929.png",
    "Pasted image 20231228123929.png"
  ]
}